LICENSE
MANIFEST.in
README.md
setup.py
batchalign/__init__.py
batchalign/__main__.py
batchalign/constants.py
batchalign/document.py
batchalign/errors.py
batchalign/version
batchalign.egg-info/PKG-INFO
batchalign.egg-info/SOURCES.txt
batchalign.egg-info/dependency_links.txt
batchalign.egg-info/entry_points.txt
batchalign.egg-info/requires.txt
batchalign.egg-info/top_level.txt
batchalign/cli/__init__.py
batchalign/cli/cache.py
batchalign/cli/cli.py
batchalign/cli/dispatch.py
batchalign/formats/__init__.py
batchalign/formats/base.py
batchalign/formats/chat/__init__.py
batchalign/formats/chat/file.py
batchalign/formats/chat/generator.py
batchalign/formats/chat/lexer.py
batchalign/formats/chat/parser.py
batchalign/formats/chat/utils.py
batchalign/formats/textgrid/__init__.py
batchalign/formats/textgrid/file.py
batchalign/formats/textgrid/generator.py
batchalign/formats/textgrid/parser.py
batchalign/models/__init__.py
batchalign/models/resolve.py
batchalign/models/utils.py
batchalign/models/speaker/__init__.py
batchalign/models/speaker/config.yaml
batchalign/models/speaker/infer.py
batchalign/models/speaker/utils.py
batchalign/models/training/__init__.py
batchalign/models/training/run.py
batchalign/models/training/utils.py
batchalign/models/utterance/__init__.py
batchalign/models/utterance/cantonese_infer.py
batchalign/models/utterance/dataset.py
batchalign/models/utterance/execute.py
batchalign/models/utterance/infer.py
batchalign/models/utterance/prep.py
batchalign/models/utterance/train.py
batchalign/models/wave2vec/__init__.py
batchalign/models/wave2vec/infer_fa.py
batchalign/models/whisper/__init__.py
batchalign/models/whisper/infer_asr.py
batchalign/models/whisper/infer_fa.py
batchalign/pipelines/__init__.py
batchalign/pipelines/base.py
batchalign/pipelines/cache.py
batchalign/pipelines/dispatch.py
batchalign/pipelines/pipeline.py
batchalign/pipelines/analysis/__init__.py
batchalign/pipelines/analysis/eval.py
batchalign/pipelines/asr/__init__.py
batchalign/pipelines/asr/num2chinese.py
batchalign/pipelines/asr/oai_whisper.py
batchalign/pipelines/asr/rev.py
batchalign/pipelines/asr/utils.py
batchalign/pipelines/asr/whisper.py
batchalign/pipelines/asr/whisperx.py
